{"Title": "SLC37A4-CDG: Mislocalization of the glucose-6-phosphate transporter to the Golgi causes a new congenital disorder of glycosylation", "Year": 2020, "Source": "Mol. Genet. Metab. Rep.", "Volume": "25", "Issue": null, "Art.No": null, "PageStart": null, "PageEnd": null, "CitedBy": 1, "DOI": "10.1016/j.ymgmr.2020.100636", "Link": "https://www.scopus.com/inward/record.uri?partnerID=HzOxMe3b&scp=85089469267&origin=inward", "Abstract": "\u00a9 2020 The Author(s)Loss-of-function of the glucose-6-phosphate transporter is caused by biallelic mutations in SLC37A4 and leads to glycogen storage disease Ib. Here we describe a second disease caused by a single dominant mutation in the same gene. The mutation abolishes the ER retention signal of the transporter and generates a weak Golgi retention signal. Intracellular mislocalization of the transporter leads to a congenital disorder of glycosylation instead of glycogen storage disease.", "AuthorKeywords": ["CDG", "Glycogen storage disease", "Glycosylation", "SLC37A4"], "IndexKeywords": null, "DocumentType": "Journal", "PublicationStage": null, "OpenAccess": 1, "EID": "2-s2.0-85089469267", "SubjectAreas": [["Molecular Biology", "BIOC", "1312"], ["Genetics", "BIOC", "1311"], ["Endocrinology", "BIOC", "1310"]], "AuthorData": {"57201870736": {"Name": "Marquardt T.", "AuthorID": "57201870736", "AffiliationID": "60006490", "AffiliationName": "University Children's Hospital M\u00fcnster, Department of General Pediatrics"}, "57021648100": {"Name": "Hogrebe M.", "AuthorID": "57021648100", "AffiliationID": "60006490", "AffiliationName": "University Children's Hospital M\u00fcnster, Department of General Pediatrics"}, "7007055489": {"Name": "Rust S.", "AuthorID": "7007055489", "AffiliationID": "60006490", "AffiliationName": "University Children's Hospital M\u00fcnster, Department of General Pediatrics"}, "35389590700": {"Name": "Reunert J.", "AuthorID": "35389590700", "AffiliationID": "60006490", "AffiliationName": "University Children's Hospital M\u00fcnster, Department of General Pediatrics"}, "6701802438": {"Name": "Gr\u00fcneberg M.", "AuthorID": "6701802438", "AffiliationID": "60006490", "AffiliationName": "University Children's Hospital M\u00fcnster, Department of General Pediatrics"}, "56196472600": {"Name": "Park J.", "AuthorID": "56196472600", "AffiliationID": "60006490", "AffiliationName": "University Children's Hospital M\u00fcnster, Department of General Pediatrics"}, "7102425347": {"Name": "Engel T.", "AuthorID": "7102425347", "AffiliationID": "60006490", "AffiliationName": "University Children's Hospital M\u00fcnster, Department of General Pediatrics"}, "7003872700": {"Name": "Bzduch V.", "AuthorID": "7003872700", "AffiliationID": "60001987", "AffiliationName": "Comenius University, National Institute of Children's Diseases, Department of Paediatrics"}, "6603342718": {"Name": "Callewaert N.", "AuthorID": "6603342718", "AffiliationID": "123387737", "AffiliationName": "Medical Biotechnology lab, Center for Medical Biotechnology"}, "7003596979": {"Name": "Lachmann R.", "AuthorID": "7003596979", "AffiliationID": "60020736", "AffiliationName": "Charles Dent Metabolic Unit Box 92, National Hospital for Neurology and Neurosurgery"}, "7403330466": {"Name": "Wada Y.", "AuthorID": "7403330466", "AffiliationID": "112773773", "AffiliationName": "Osaka Women's and Children's Hospital"}}}