{"Title": "Job dissatisfaction, \u2018burnout\u2019 and alienation of labour: undercurrents in England\u2019s NHS", "Year": 2019, "Source": "J. R. Soc. Med.", "Volume": "112", "Issue": 9, "Art.No": null, "PageStart": 370, "PageEnd": 377, "CitedBy": 4, "DOI": "10.1177/0141076819855956", "Link": "https://www.scopus.com/inward/record.uri?partnerID=HzOxMe3b&scp=85071963597&origin=inward", "Abstract": null, "AuthorKeywords": null, "IndexKeywords": ["Burnout, Professional", "England", "Humans", "Job Satisfaction", "Longitudinal Studies", "Nursing Assistants", "Retrospective Studies", "State Medicine", "Workforce"], "DocumentType": "Journal", "PublicationStage": null, "OpenAccess": 0, "EID": "2-s2.0-85071963597", "SubjectAreas": [["Medicine (all)", "MEDI", "2700"]], "AuthorData": {"57220420292": {"Name": "Iliffe S.", "AuthorID": "57220420292", "AffiliationID": "60022148", "AffiliationName": "Research Department of Primary Care & Population Health, Univeristy College London"}, "57202296197": {"Name": "Manthorpe J.", "AuthorID": "57202296197", "AffiliationID": "60011520", "AffiliationName": "NIHR Health and Social Care Workforce Research Unit, King's College London WC2B 6LE"}}}