{"Title": "Genetic copy number variants, cognition and psychosis: a meta-analysis and a family study", "Year": 2020, "Source": "Mol. Psychiatry", "Volume": null, "Issue": null, "Art.No": null, "PageStart": null, "PageEnd": null, "CitedBy": 0, "DOI": "10.1038/s41380-020-0820-7", "Link": "https://www.scopus.com/inward/record.uri?partnerID=HzOxMe3b&scp=85088661130&origin=inward", "Abstract": "\u00a9 2020, The Author(s).The burden of large and rare copy number genetic variants (CNVs) as well as certain specific CNVs increase the risk of developing schizophrenia. Several cognitive measures are purported schizophrenia endophenotypes and may represent an intermediate point between genetics and the illness. This paper investigates the influence of CNVs on cognition. We conducted a systematic review and meta-analysis of the literature exploring the effect of CNV burden on general intelligence. We included ten primary studies with a total of 18,847 participants and found no evidence of association. In a new psychosis family study, we investigated the effects of CNVs on specific cognitive abilities. We examined the burden of large and rare CNVs (>200 kb, <1% MAF) as well as known schizophrenia-associated CNVs in patients with psychotic disorders, their unaffected relatives and controls (N = 3428) from the Psychosis Endophenotypes International Consortium (PEIC). The carriers of specific schizophrenia-associated CNVs showed poorer performance than non-carriers in immediate (P = 0.0036) and delayed (P = 0.0115) verbal recall. We found suggestive evidence that carriers of schizophrenia-associated CNVs had poorer block design performance (P = 0.0307). We do not find any association between CNV burden and cognition. Our findings show that the known high-risk CNVs are not only associated with schizophrenia and other neurodevelopmental disorders, but are also a contributing factor to impairment in cognitive domains such as memory and perceptual reasoning, and act as intermediate biomarkers of disease risk.", "AuthorKeywords": null, "IndexKeywords": null, "DocumentType": "Journal", "PublicationStage": null, "OpenAccess": 1, "EID": "2-s2.0-85088661130", "SubjectAreas": [["Molecular Biology", "BIOC", "1312"], ["Psychiatry and Mental Health", "MEDI", "2738"], ["Cellular and Molecular Neuroscience", "NEUR", "2804"]], "AuthorData": {"42162169300": {"Name": "Thygesen J.H.", "AuthorID": "42162169300", "AffiliationID": "60022148", "AffiliationName": "Division of Psychiatry, University College London"}, "57202158979": {"Name": "Presman A.", "AuthorID": "57202158979", "AffiliationID": "60022148", "AffiliationName": "Division of Psychiatry, University College London"}, "57214795159": {"Name": "Harju-Sepp\u00e4nen J.", "AuthorID": "57214795159", "AffiliationID": "60022148", "AffiliationName": "Division of Psychiatry, University College London"}, "24528118700": {"Name": "Irizar H.", "AuthorID": "24528118700", "AffiliationID": "60022148", "AffiliationName": "Division of Psychiatry, University College London"}, "57192098590": {"Name": "Jones R.", "AuthorID": "57192098590", "AffiliationID": "60022148", "AffiliationName": "Division of Psychiatry, University College London"}, "35976214200": {"Name": "Kuchenbaecker K.", "AuthorID": "35976214200", "AffiliationID": "60022148", "AffiliationName": "UCL Genetics Institute, University College London"}, "57214801812": {"Name": "Austin-Zimmerman I.", "AuthorID": "57214801812", "AffiliationID": "60022148", "AffiliationName": "Division of Psychiatry, University College London"}, "57214801434": {"Name": "Bhat A.", "AuthorID": "57214801434", "AffiliationID": "60022148", "AffiliationName": "Division of Psychiatry, University College London"}, "57215540464": {"Name": "Calafato S.", "AuthorID": "57215540464", "AffiliationID": "60022148", "AffiliationName": "Division of Psychiatry, University College London"}, "57218297299": {"Name": "D\u00edez-Revuelta \u00c1.", "AuthorID": "57218297299", "AffiliationID": "60108440, 60027282, 60028442", "AffiliationName": "Laboratory of Cognitive and Computational Neuroscience\u2014Centre for Biomedical Technology (CTB), Complutense University and Technical University of Madrid"}, "57214356802": {"Name": "McQuillin A.", "AuthorID": "57214356802", "AffiliationID": "60022148", "AffiliationName": "Division of Psychiatry, University College London"}, "57218290295": {"Name": "Muir R.", "AuthorID": "57218290295", "AffiliationID": "60022148", "AffiliationName": "Division of Psychiatry, University College London"}, "56015642200": {"Name": "Ranlund S.", "AuthorID": "56015642200", "AffiliationID": "60011520", "AffiliationName": "Institute of Psychiatry, Psychology & Neuroscience at King\u2019s College London"}, "57219712335": {"Name": "Walshe M.", "AuthorID": "57219712335", "AffiliationID": "60022148", "AffiliationName": "Division of Psychiatry, University College London"}, "57196455458": {"Name": "Zartaloudi E.", "AuthorID": "57196455458", "AffiliationID": "60022148", "AffiliationName": "Division of Psychiatry, University College London"}, "7007065687": {"Name": "Bell V.", "AuthorID": "7007065687", "AffiliationID": "60022148", "AffiliationName": "Division of Psychiatry, University College London"}, "57216064872": {"Name": "Bramon E.", "AuthorID": "57216064872", "AffiliationID": "60022148, 60109771", "AffiliationName": "Institute of Cognitive Neuroscience, University College London"}, "57193456554": {"Name": "Lin K.", "AuthorID": "57193456554", "AffiliationID": "60002634, 60026851", "AffiliationName": "Nuffield Department of Population Health, University of Oxford"}, "10738849300": {"Name": "Di Forti M.", "AuthorID": "10738849300", "AffiliationID": "60011520", "AffiliationName": "Institute of Psychiatry, Psychology & Neuroscience at King\u2019s College London"}, "6508180775": {"Name": "Iyegbe C.", "AuthorID": "6508180775", "AffiliationID": "60011520", "AffiliationName": "Institute of Psychiatry, Psychology & Neuroscience at King\u2019s College London"}, "56007899300": {"Name": "Kravariti E.", "AuthorID": "56007899300", "AffiliationID": "60011520", "AffiliationName": "Institute of Psychiatry, Psychology & Neuroscience at King\u2019s College London"}, "6507443795": {"Name": "Picchioni M.", "AuthorID": "6507443795", "AffiliationID": "60011520", "AffiliationName": "Institute of Psychiatry, Psychology & Neuroscience at King\u2019s College London"}, "14632352500": {"Name": "Prata D.P.", "AuthorID": "14632352500", "AffiliationID": "60028300", "AffiliationName": "Centre for Psychological Research and Social Intervention, ISCTE-IUL"}, "7103137549": {"Name": "Schulze K.", "AuthorID": "7103137549", "AffiliationID": "60028884", "AffiliationName": "South London and Maudsley NHS Foundation Trust"}, "8855468700": {"Name": "Toulopoulou T.", "AuthorID": "8855468700", "AffiliationID": "60014808", "AffiliationName": "Department of Psychology, Bilkent University"}, "7102358027": {"Name": "van Os J.", "AuthorID": "7102358027", "AffiliationID": "60032724", "AffiliationName": "Department of Psychiatry, UMC Utrecht Brain Center"}, "55961024500": {"Name": "Vassos E.", "AuthorID": "55961024500", "AffiliationID": "60011520", "AffiliationName": "Institute of Psychiatry, Psychology & Neuroscience at King\u2019s College London"}, "57215194978": {"Name": "Powell J.", "AuthorID": "57215194978", "AffiliationID": "60011520", "AffiliationName": "Institute of Psychiatry, Psychology & Neuroscience at King\u2019s College London"}, "7402975073": {"Name": "Lewis C.M.", "AuthorID": "7402975073", "AffiliationID": "60011520", "AffiliationName": "Institute of Psychiatry, Psychology & Neuroscience at King\u2019s College London"}, "57219715244": {"Name": "Murray R.M.", "AuthorID": "57219715244", "AffiliationID": "60028884", "AffiliationName": "South London and Maudsley NHS Foundation Trust"}, "57204416905": {"Name": "Alizadeh B.Z.", "AuthorID": "57204416905", "AffiliationID": "60006027", "AffiliationName": "Department of Epidemiology, University Medical Center Groningen"}, "57211720387": {"Name": "Bartels-Velthuis A.", "AuthorID": "57211720387", "AffiliationID": "60006027, 60010023", "AffiliationName": "University of Groningen, University Medical Center Groningen, University Center for Psychiatry, Rob Giel Research Center"}, "57218240495": {"Name": "Bruggeman R.", "AuthorID": "57218240495", "AffiliationID": "60010023", "AffiliationName": "Department of Clinical and Developmental Neuropsychology, University of Groningen"}, "56099614300": {"Name": "Cahn W.", "AuthorID": "56099614300", "AffiliationID": "112771723", "AffiliationName": "Altrecht, General Mental Health Care"}, "57191504132": {"Name": "de Zwarte S.M.C.", "AuthorID": "57191504132", "AffiliationID": "60032724, 60007989", "AffiliationName": "University Medical Center Utrecht, Department of Psychiatry, Brain Centre Rudolf Magnus, Utrecht University"}, "57213374467": {"Name": "Kahn R.", "AuthorID": "57213374467", "AffiliationID": "60012981", "AffiliationName": "Department of Psychiatry, Icahn School of Medicine at Mount Sinai"}, "26024266200": {"Name": "Luykx J.J.", "AuthorID": "26024266200", "AffiliationID": "124500919", "AffiliationName": "Second opinion outpatient clinic, GGNet Mental Health"}, "57202687835": {"Name": "van Haren N.", "AuthorID": "57202687835", "AffiliationID": "60015627, 60032114", "AffiliationName": "Department of Child and Adolescent Psychiatry/Psychology, Erasmus University Medical Center, Sophia\u2019s Children Hospital"}, "6603814621": {"Name": "Crespo-Facorro B.", "AuthorID": "6603814621", "AffiliationID": "60033267, 60033284, 60103764", "AffiliationName": "Hospital Universitario Virgen del Roc\u00edo, IBiS, Department of Psychiatry, School of Medicine, University of Sevilla"}, "9638989000": {"Name": "Mata I.", "AuthorID": "9638989000", "AffiliationID": "100498763", "AffiliationName": "Fundaci\u00f3n Argibide"}, "7005592387": {"Name": "de Haan L.", "AuthorID": "7005592387", "AffiliationID": "120975141", "AffiliationName": "Arkin, Institute for Mental Health"}, "57209521572": {"Name": "Schirmbeck F.", "AuthorID": "57209521572", "AffiliationID": "120975141", "AffiliationName": "Arkin, Institute for Mental Health"}, "22034087100": {"Name": "Hall J.", "AuthorID": "22034087100", "AffiliationID": "60023998", "AffiliationName": "School of Medicine, Cardiff University, Hadyn Ellis Building"}, "57216386156": {"Name": "Hall M.H.", "AuthorID": "57216386156", "AffiliationID": "60015527, 60002746", "AffiliationName": "Psychosis Neurobiology Laboratory, Harvard Medical School, McLean Hospital"}, "57193557208": {"Name": "Jablensky A.", "AuthorID": "57193557208", "AffiliationID": "60009834, 60031806", "AffiliationName": "Centre for Clinical Research in Neuropsychiatry, The University of Western Australia"}, "7006320678": {"Name": "Kalaydjieva L.", "AuthorID": "7006320678", "AffiliationID": "60031806, 60005202", "AffiliationName": "Harry Perkins Institute of Medical Research and Centre for Medical Research, The University of Western Australia"}, "7006525184": {"Name": "Lawrie S.", "AuthorID": "7006525184", "AffiliationID": "60027272, 60009383", "AffiliationName": "Division of Psychiatry, University of Edinburgh, Royal Edinburgh Hospital"}, "56208173500": {"Name": "McIntosh A.M.", "AuthorID": "56208173500", "AffiliationID": "60027272", "AffiliationName": "Centre for Cognitive Ageing and Cognitive Epidemiology, University of Edinburgh"}, "8749594800": {"Name": "McDonald C.", "AuthorID": "8749594800", "AffiliationID": "60008539", "AffiliationName": "The Centre for Neuroimaging & Cognitive Genomics (NICOG) and NCBES Galway Neuroscience Centre, National University of Ireland Galway"}, "57216386018": {"Name": "Ophoff R.", "AuthorID": "57216386018", "AffiliationID": "60032114", "AffiliationName": "Department of Psychiatry, Erasmus MC University Medical Center Rotterdam"}, "57202558782": {"Name": "Rujescu D.", "AuthorID": "57202558782", "AffiliationID": "60014059", "AffiliationName": "Department of Psychiatry, Psychotherapy and Psychosomatics, University of Halle Wittenberg"}, "6603411181": {"Name": "Rutten B.P.F.", "AuthorID": "6603411181", "AffiliationID": "60007895", "AffiliationName": "The Brain+Nerve Centre, Maastricht University Medical Centre+ (MUMC+)"}, "57209521574": {"Name": "Simons C.J.P.", "AuthorID": "57209521574", "AffiliationID": "60028963", "AffiliationName": "GGzE Institute for Mental Health Care"}, "6701774874": {"Name": "van Amelsvoort T.", "AuthorID": "6701774874", "AffiliationID": "60018869", "AffiliationName": "Department of Psychiatry & Neuropsychology, School for Mental Health and Neuroscience, Maastricht University Medical Centre"}, "24377053800": {"Name": "Shaikh M.", "AuthorID": "24377053800", "AffiliationID": "60022148", "AffiliationName": "Research Department of Clinical, Educational and Health Psychology, University College London"}, "57211720800": {"Name": "van Winkel R.", "AuthorID": "57211720800", "AffiliationID": "60025063", "AffiliationName": "KU Leuven, Department of Neuroscience, Research Group Psychiatry"}, "7003679476": {"Name": "Weisbrod M.", "AuthorID": "7003679476", "AffiliationID": "101556041", "AffiliationName": "SRH Klinikum"}}}