{"Title": "Evidence synthesis communities in low-income and middle-income countries and the COVID-19 response", "Year": 2020, "Source": "Lancet", "Volume": "396", "Issue": 10262, "Art.No": null, "PageStart": 1539, "PageEnd": 1541, "CitedBy": 1, "DOI": "10.1016/S0140-6736(20)32141-3", "Link": "https://www.scopus.com/inward/record.uri?partnerID=HzOxMe3b&scp=85095445633&origin=inward", "Abstract": null, "AuthorKeywords": null, "IndexKeywords": ["Betacoronavirus", "Communicable Disease Control", "Coronavirus Infections", "Developing Countries", "Humans", "International Cooperation", "Pandemics", "Pneumonia, Viral"], "DocumentType": "Journal", "PublicationStage": null, "OpenAccess": 1, "EID": "2-s2.0-85095445633", "SubjectAreas": [["Medicine (all)", "MEDI", "2700"]], "AuthorData": {"8604870700": {"Name": "Stewart R.", "AuthorID": "8604870700", "AffiliationID": "60000717", "AffiliationName": "Africa Centre for Evidence, University of Johannesburg"}, "57202999951": {"Name": "El-Harakeh A.", "AuthorID": "57202999951", "AffiliationID": "60068761", "AffiliationName": "Center for Systematic Reviews of Health Policy and Systems Research (SPARK), American University of Beirut"}, "57219778341": {"Name": "Cherian S.A.", "AuthorID": "57219778341", "AffiliationID": "118643594", "AffiliationName": "Pushpagiri Centre for Evidence-Based Practice, Pushpagiri Institute of Medical Sciences and Research Center"}}}