{"Title": "Do smokers want to protect non-smokers from the harms of second-hand smoke in cars? Findings from the EUREST-PLUS ITC Europe Surveys", "Year": 2020, "Source": "Eur. J. Public Health", "Volume": "30", "Issue": null, "Art.No": null, "PageStart": null, "PageEnd": null, "CitedBy": 0, "DOI": "10.1093/eurpub/ckaa056", "Link": "https://www.scopus.com/inward/record.uri?partnerID=HzOxMe3b&scp=85090920675&origin=inward", "Abstract": "\u00a9 The Author(s) 2020. Published by Oxford University Press on behalf of the European Public Health Association. All rights reserved.Background: There is currently no comprehensive legislation protecting non-smokers and children from secondhand smoke (SHS) exposure in private cars at the European Union (EU) level. This study aims to assess smokers\u2019 support for smoke-free cars legislation in six EU countries. Methods: Data come from the EUREST-PLUS ITC Europe Surveys: Wave 1 (2016, n \u00bc 6011) and Wave 2 (2018, n \u00bc 6027) conducted in Germany, Greece, Hungary, Poland, Romania and Spain. Support for smoke-free cars carrying pre-school children and non-smokers and voluntary implementation of smoke-free cars were assessed among adult smokers. Generalized estimating equations models were used to assess changes in support between waves. Results: In 2018, 96.3% [95% confidence interval (CI) 95.4\u201397.0%] of the overall sample supported smoke-free legislation for cars carrying pre-school children, representing an increase of 2.4 percentage points in comparison to 2016. Smoke-free legislation for cars transporting non-smokers was supported by 85.2% (95% CI 83.1\u201387.1%) of smokers\u2019 in 2016 and 90.2% (95% CI 88.6\u201391.7%) in 2018. Among smokers who owned cars, there was a significant 7.2 percentage points increase in voluntary implementation of smoke-free cars carrying children from 2016 (60.7%, 95% CI 57.2\u201364.0%) to 2018 (67.9%, 95% CI 65.1\u201370.5%). All sociodemographic groups of smokers reported support higher than 80% in 2018. Conclusion: The vast majority of smokers in all six EU countries support smoke-free legislation for cars carrying pre-school children and non-smokers. This almost universal support across countries and sociodemographic groups is a clear indicator of a window of opportunity for the introduction of comprehensive legislation to protect non-smokers and children from SHS exposure in cars.", "AuthorKeywords": null, "IndexKeywords": null, "DocumentType": "Journal", "PublicationStage": null, "OpenAccess": 0, "EID": "2-s2.0-85090920675", "SubjectAreas": [["Public Health, Environmental and Occupational Health", "MEDI", "2739"]], "AuthorData": {"57210467946": {"Name": "Nogueira S.O.", "AuthorID": "57210467946", "AffiliationID": "60102756", "AffiliationName": "Consortium for Biomedical Research in Respiratory Diseases (CIBERES)"}, "57195941806": {"Name": "Tigova O.", "AuthorID": "57195941806", "AffiliationID": "60102756", "AffiliationName": "Consortium for Biomedical Research in Respiratory Diseases (CIBERES)"}, "24474718500": {"Name": "Fu M.", "AuthorID": "24474718500", "AffiliationID": "60102756", "AffiliationName": "Consortium for Biomedical Research in Respiratory Diseases (CIBERES)"}, "55597087956": {"Name": "Fern\u00e1ndez E.", "AuthorID": "55597087956", "AffiliationID": "60102756", "AffiliationName": "Consortium for Biomedical Research in Respiratory Diseases (CIBERES)"}, "57201397811": {"Name": "Castellano Y.", "AuthorID": "57201397811", "AffiliationID": "60015633", "AffiliationName": "Tobacco Control Unit, Catalan Institute of Oncology (ICO), L'Hospitalet de Llobregat"}, "15838780300": {"Name": "Driezen P.", "AuthorID": "15838780300", "AffiliationID": "60014171", "AffiliationName": "University of Waterloo (UW)"}, "36619072500": {"Name": "Quah A.C.K.", "AuthorID": "36619072500", "AffiliationID": "60014171", "AffiliationName": "Department of Psychology, University of Waterloo (UW)"}, "7004978760": {"Name": "Fong G.T.", "AuthorID": "7004978760", "AffiliationID": "60014171", "AffiliationName": "University of Waterloo (UW)"}, "57221185233": {"Name": "Kyriakos C.N.", "AuthorID": "57221185233", "AffiliationID": "60012413, 60001524", "AffiliationName": "School of Medicine, University of Crete (UoC)"}, "13410362100": {"Name": "Vardavas C.I.", "AuthorID": "13410362100", "AffiliationID": "60012413, 60001524", "AffiliationName": "School of Medicine, University of Crete (UoC)"}, "57219993603": {"Name": "Glahn A.", "AuthorID": "57219993603", "AffiliationID": "121631912", "AffiliationName": "European Network for Smoking and Tobacco Prevention (ENSP)"}, "57202597551": {"Name": "Nguyen D.", "AuthorID": "57202597551", "AffiliationID": "121631912", "AffiliationName": "European Network for Smoking and Tobacco Prevention (ENSP)"}, "57211020403": {"Name": "Nikitara K.", "AuthorID": "57211020403", "AffiliationID": "121631912", "AffiliationName": "European Network for Smoking and Tobacco Prevention (ENSP)"}, "8316224000": {"Name": "Radu-Loghin C.", "AuthorID": "8316224000", "AffiliationID": "121631912", "AffiliationName": "European Network for Smoking and Tobacco Prevention (ENSP)"}, "57211062707": {"Name": "Starchenko P.", "AuthorID": "57211062707", "AffiliationID": "121631912", "AffiliationName": "European Network for Smoking and Tobacco Prevention (ENSP)"}, "35596169100": {"Name": "Tsatsakis A.", "AuthorID": "35596169100", "AffiliationID": "60012413, 60001524", "AffiliationName": "School of Medicine, University of Crete (UoC)"}, "55353191500": {"Name": "Girvalaki C.", "AuthorID": "55353191500", "AffiliationID": "60012413, 60001524", "AffiliationName": "School of Medicine, University of Crete (UoC)"}, "57219992272": {"Name": "Igoumenaki C.", "AuthorID": "57219992272", "AffiliationID": "60012413, 60001524", "AffiliationName": "School of Medicine, University of Crete (UoC)"}, "8392958100": {"Name": "Papadakis S.", "AuthorID": "8392958100", "AffiliationID": "60012413, 60001524", "AffiliationName": "School of Medicine, University of Crete (UoC)"}, "57219990564": {"Name": "Papathanasaki A.", "AuthorID": "57219990564", "AffiliationID": "60012413, 60001524", "AffiliationName": "School of Medicine, University of Crete (UoC)"}, "6602176665": {"Name": "Tzatzarakis M.", "AuthorID": "6602176665", "AffiliationID": "60012413, 60001524", "AffiliationName": "School of Medicine, University of Crete (UoC)"}, "56151751500": {"Name": "Vardavas A.I.", "AuthorID": "56151751500", "AffiliationID": "60012413, 60001524", "AffiliationName": "School of Medicine, University of Crete (UoC)"}, "55332765500": {"Name": "Zato\u0144ski M.", "AuthorID": "55332765500", "AffiliationID": "124543459", "AffiliationName": "European Observatory of Health Inequalities, President Stanislaw, Wojciechowski State University of Applied Sciences"}, "6602321502": {"Name": "Przewo\u017aniak K.", "AuthorID": "6602321502", "AffiliationID": "60007327", "AffiliationName": "Collegium Civitas"}, "55849657500": {"Name": "Herbe\u0107 A.", "AuthorID": "55849657500", "AffiliationID": "107948960", "AffiliationName": "Health Promotion Foundation (HPF)"}, "55155610300": {"Name": "Janik-Koncewicz K.", "AuthorID": "55155610300", "AffiliationID": "107948960", "AffiliationName": "Health Promotion Foundation (HPF)"}, "11940097400": {"Name": "Mons U.", "AuthorID": "11940097400", "AffiliationID": "60017059", "AffiliationName": "German Cancer Research Center (DKFZ), Cancer Prevention Unit, WHO Collaborating Centre for Tobacco Control"}, "35783090900": {"Name": "Kahnert S.", "AuthorID": "35783090900", "AffiliationID": "60017059", "AffiliationName": "German Cancer Research Center (DKFZ), Cancer Prevention Unit, WHO Collaborating Centre for Tobacco Control"}, "57200380512": {"Name": "Demj\u00e9n T.", "AuthorID": "57200380512", "AffiliationID": "123001610", "AffiliationName": "Smoking or Health Hungarian Foundation (SHHF)"}, "57210469182": {"Name": "Kiss J.", "AuthorID": "57210469182", "AffiliationID": "123001610", "AffiliationName": "Smoking or Health Hungarian Foundation (SHHF)"}, "57219990952": {"Name": "Kovacs A.P.", "AuthorID": "57219990952", "AffiliationID": "123001610", "AffiliationName": "Smoking or Health Hungarian Foundation (SHHF)"}, "6603197784": {"Name": "Trofor A.C.", "AuthorID": "6603197784", "AffiliationID": "123002108", "AffiliationName": "Aer Pur Romania"}, "57210475549": {"Name": "Eremia M.", "AuthorID": "57210475549", "AffiliationID": "123002108", "AffiliationName": "Aer Pur Romania"}, "8595151300": {"Name": "Lotrean L.", "AuthorID": "8595151300", "AffiliationID": "123002108", "AffiliationName": "Aer Pur Romania"}, "57220360696": {"Name": "Mihaltan F.", "AuthorID": "57220360696", "AffiliationID": "123002108", "AffiliationName": "Aer Pur Romania"}, "8742801000": {"Name": "Katsaounou P.A.", "AuthorID": "8742801000", "AffiliationID": "112145328", "AffiliationName": "European Respiratory Society"}, "7003809974": {"Name": "Tountas Y.", "AuthorID": "7003809974", "AffiliationID": "60028900, 60064532", "AffiliationName": "First ICU Evaggelismos Hospital Athens, National and Kapodistrian University of Athens (UoA)"}, "56185873000": {"Name": "Behrakis P.", "AuthorID": "56185873000", "AffiliationID": "60028900, 60064532", "AffiliationName": "First ICU Evaggelismos Hospital Athens, National and Kapodistrian University of Athens (UoA)"}, "57221183585": {"Name": "Filippidis F.T.", "AuthorID": "57221183585", "AffiliationID": "60028900, 60064532", "AffiliationName": "First ICU Evaggelismos Hospital Athens, National and Kapodistrian University of Athens (UoA)"}, "6602154890": {"Name": "Gratziou C.", "AuthorID": "6602154890", "AffiliationID": "60028900, 60064532", "AffiliationName": "First ICU Evaggelismos Hospital Athens, National and Kapodistrian University of Athens (UoA)"}, "57219992840": {"Name": "Katsaounou P.", "AuthorID": "57219992840", "AffiliationID": "60028900, 60064532", "AffiliationName": "First ICU Evaggelismos Hospital Athens, National and Kapodistrian University of Athens (UoA)"}, "56707423100": {"Name": "Peleki T.", "AuthorID": "56707423100", "AffiliationID": "60028900, 60064532", "AffiliationName": "First ICU Evaggelismos Hospital Athens, National and Kapodistrian University of Athens (UoA)"}, "57210470671": {"Name": "Petroulia I.", "AuthorID": "57210470671", "AffiliationID": "60028900, 60064532", "AffiliationName": "First ICU Evaggelismos Hospital Athens, National and Kapodistrian University of Athens (UoA)"}, "23053290100": {"Name": "Tzavara C.", "AuthorID": "23053290100", "AffiliationID": "60028900, 60064532", "AffiliationName": "First ICU Evaggelismos Hospital Athens, National and Kapodistrian University of Athens (UoA)"}, "57219993062": {"Name": "Rohde G.", "AuthorID": "57219993062", "AffiliationID": "112145328", "AffiliationName": "European Respiratory Society"}, "57219990748": {"Name": "Asano T.", "AuthorID": "57219990748", "AffiliationID": "112145328", "AffiliationName": "European Respiratory Society"}, "57219992638": {"Name": "Cichon C.", "AuthorID": "57219992638", "AffiliationID": "112145328", "AffiliationName": "European Respiratory Society"}, "57219994367": {"Name": "Far A.", "AuthorID": "57219994367", "AffiliationID": "112145328", "AffiliationName": "European Respiratory Society"}, "57219992677": {"Name": "Genton C.", "AuthorID": "57219992677", "AffiliationID": "112145328", "AffiliationName": "European Respiratory Society"}, "57219991726": {"Name": "Jessner M.", "AuthorID": "57219991726", "AffiliationID": "112145328", "AffiliationName": "European Respiratory Society"}, "15837063900": {"Name": "Hedman L.", "AuthorID": "15837063900", "AffiliationID": "112145328", "AffiliationName": "European Respiratory Society"}, "56521083600": {"Name": "Janson C.", "AuthorID": "56521083600", "AffiliationID": "112145328", "AffiliationName": "European Respiratory Society"}, "56785344400": {"Name": "Lindberg A.", "AuthorID": "56785344400", "AffiliationID": "112145328", "AffiliationName": "European Respiratory Society"}, "57219993459": {"Name": "Maguire B.", "AuthorID": "57219993459", "AffiliationID": "112145328", "AffiliationName": "European Respiratory Society"}, "53164833700": {"Name": "Ravara S.", "AuthorID": "53164833700", "AffiliationID": "112145328", "AffiliationName": "European Respiratory Society"}, "57219991764": {"Name": "Vaccaro V.", "AuthorID": "57219991764", "AffiliationID": "112145328", "AffiliationName": "European Respiratory Society"}, "55339576700": {"Name": "Ward B.", "AuthorID": "55339576700", "AffiliationID": "112145328", "AffiliationName": "European Respiratory Society"}, "57210473220": {"Name": "B\u00e9cuwe N.", "AuthorID": "57210473220", "AffiliationID": "125398007", "AffiliationName": "Kantar Public"}, "57219991207": {"Name": "Deaconu L.", "AuthorID": "57219991207", "AffiliationID": "125398007", "AffiliationName": "Kantar Public"}, "57219990624": {"Name": "Goudet S.", "AuthorID": "57219990624", "AffiliationID": "125398007", "AffiliationName": "Kantar Public"}, "57219990377": {"Name": "Hanley C.", "AuthorID": "57219990377", "AffiliationID": "125398007", "AffiliationName": "Kantar Public"}, "57219991888": {"Name": "Rivi\u00e8re O.", "AuthorID": "57219991888", "AffiliationID": "125398007", "AffiliationName": "Kantar Public"}, "35398346200": {"Name": "McNeill A.", "AuthorID": "35398346200", "AffiliationID": "60011520", "AffiliationName": "Kings College London (KCL)"}, "57194228467": {"Name": "East K.", "AuthorID": "57194228467", "AffiliationID": "60011520", "AffiliationName": "Kings College London (KCL)"}, "35069510500": {"Name": "Hitchman S.C.", "AuthorID": "35069510500", "AffiliationID": "60011520", "AffiliationName": "Kings College London (KCL)"}, "7004296730": {"Name": "Willemsen M.", "AuthorID": "7004296730", "AffiliationID": "60018869", "AffiliationName": "Maastricht University (UM)"}, "55537157500": {"Name": "De Vries H.", "AuthorID": "55537157500", "AffiliationID": "60018869", "AffiliationName": "Maastricht University (UM)"}, "55556825600": {"Name": "Hummel K.", "AuthorID": "55556825600", "AffiliationID": "60018869", "AffiliationName": "Maastricht University (UM)"}, "36168524700": {"Name": "Nagelhout G.E.", "AuthorID": "36168524700", "AffiliationID": "60018869", "AffiliationName": "Maastricht University (UM)"}, "57210464155": {"Name": "Agar T.K.", "AuthorID": "57210464155", "AffiliationID": "60014171", "AffiliationName": "University of Waterloo (UW)"}, "57195272227": {"Name": "Gravely S.", "AuthorID": "57195272227", "AffiliationID": "60014171", "AffiliationName": "University of Waterloo (UW)"}, "7404622193": {"Name": "Thompson M.E.", "AuthorID": "7404622193", "AffiliationID": "60014171", "AffiliationName": "University of Waterloo (UW)"}, "null": {"Name": null, "AuthorID": null, "AffiliationID": null, "AffiliationName": null}}}